mux_demux/demux1x8.v
`timescale 1ns/1ps

module demux1x8 (
    input wire in,           // Single input
    input wire [2:0] sel,   // 3-bit selection input
    output reg [7:0] out    // 8 outputs
);

    always @(*) begin
        // Default all outputs to 0
        out = 8'b00000000;

        // Route input to selected output
        case (sel)
            3'b000: out[0] = in;
            3'b001: out[1] = in;
            3'b010: out[2] = in;
            3'b011: out[3] = in;
            3'b100: out[4] = in;
            3'b101: out[5] = in;
            3'b110: out[6] = in;
            3'b111: out[7] = in;
        endcase
    end
endmodule

mux_demux/tb_demux1x8.v
module tb_demux1x8;
    reg in;
    reg [2:0] sel;
    wire [7:0] out;

    demux1x8 uut (
        .in(in),
        .sel(sel),
        .out(out)
    );

    initial begin
        // Initialize inputs
        in = 1'b0;
        sel = 3'b000;

        // Monitor outputs
        $monitor("Time: %0dns, sel: %b, in: %b, out: %b", $time, sel, in, out);

        // Test different selections
        #10 in = 1'b1; sel = 3'b000; // Route to out[0]
        #10 sel = 3'b001; // Route to out[1]
        #10 sel = 3'b010; // Route to out[2]
        #10 sel = 3'b011; // Route to out[3]
        #10 sel = 3'b100; // Route to out[4]
        #10 sel = 3'b101; // Route to out[5]
        #10 sel = 3'b110; // Route to out[6]
        #10 sel = 3'b111; // Route to out[7]

        // Reset input and check outputs
        #10 in = 1'b0; sel = 3'b000; // All outputs should be 0
        #10;

        $finish;
    end

    initial begin
        $dumpfile("demux1x8.vcd");
        $dumpvars(0, tb_demux1x8);
    end
endmodule

mux_demux/demux1x8.vcd
$date
	Wed Oct  9 23:01:01 2024
$end
$version
	Icarus Verilog
$end
$timescale
	1ps
$end
$scope module tb_demux1x8 $end
$var wire 8 ! out [7:0] $end
$var reg 1 " in $end
$var reg 3 # sel [2:0] $end
$scope module uut $end
$var wire 1 " in $end
$var wire 3 $ sel [2:0] $end
$var reg 8 % out [7:0] $end
$upscope $end
$upscope $end
$enddefinitions $end
$comment Show the parameter values. $end
$dumpall
$end
#0
$dumpvars
b0 %
b0 $
b0 #
0"
b0 !
$end
#10000
b1 !
b1 %
1"
#20000
b10 !
b10 %
b1 #
b1 $
#30000
b100 !
b100 %
b10 #
b10 $
#40000
b1000 !
b1000 %
b11 #
b11 $
#50000
b10000 !
b10000 %
b100 #
b100 $
#60000
b100000 !
b100000 %
b101 #
b101 $
#70000
b1000000 !
b1000000 %
b110 #
b110 $
#80000
b10000000 !
b10000000 %
b111 #
b111 $
#90000
b0 !
b0 %
b0 #
b0 $
0"
