mux_demux/mux8x1.v
`timescale 1ns/1ps
module mux8x1(
    input wire [7:0] in,
    input wire [2:0] sel,
    output reg out
);

    always @(*) begin
        case(sel)
            3'b000: out = in[0];
            3'b001: out = in[1];
            3'b010: out = in[2];
            3'b011: out = in[3];
            3'b100: out = in[4];
            3'b101: out = in[5];
            3'b110: out = in[6];
            3'b111: out = in[7];
        endcase
    end
endmodule

mux_demux/tb_mux8x1.v
module tb_mux8x1;
    reg [7:0] in;
    reg [2:0] sel;
    wire out;
    
    mux8x1 uut(.in(in), .sel(sel), .out(out));

    initial begin
        in = 8'b01010101;
        sel = 3'b000; 

        $monitor("Time: %0dns, sel: %b, out: %b", $time, sel, out);

        #10 sel = 3'b000; 
        #10 sel = 3'b001; 
        #10 sel = 3'b010; 
        #10 sel = 3'b011; 
        #10 sel = 3'b100; 
        #10 sel = 3'b101; 
        #10 sel = 3'b110; 
        #10 sel = 3'b111;

        #10;
        $finish;
    end

    initial begin
        $dumpfile("mux8x1.vcd");
        $dumpvars(0, tb_mux8x1);
    end
endmodule

mux_demux/mux8x1.vcd
$date
	Wed Oct  9 22:56:31 2024
$end
$version
	Icarus Verilog
$end
$timescale
	1ps
$end
$scope module tb_mux8x1 $end
$var wire 1 ! out $end
$var reg 8 " in [7:0] $end
$var reg 3 # sel [2:0] $end
$scope module uut $end
$var wire 8 $ in [7:0] $end
$var wire 3 % sel [2:0] $end
$var reg 1 ! out $end
$upscope $end
$upscope $end
$enddefinitions $end
$comment Show the parameter values. $end
$dumpall
$end
#0
$dumpvars
b0 %
b1010101 $
b0 #
b1010101 "
1!
$end
#10000
0!
b1 #
b1 %
#20000
1!
b10 #
b10 %
#30000
0!
b11 #
b11 %
#40000
1!
b100 #
b100 %
#50000
0!
b101 #
b101 %
#60000
1!
b110 #
b110 %
#70000
0!
b111 #
b111 %
