up_down_counter/up_down_counter.v
`timescale 1ns/1ps

module up_down_counter (
    input wire clk,          // Clock input
    input wire reset,        // Asynchronous reset
    input wire up_down,      // Up/Down control signal (1 for up, 0 for down)
    output reg [3:0] count   // 4-bit count output
);

    // Synchronous counter
    always @(posedge clk or posedge reset) begin
        if (reset) begin
            count <= 4'b0000; // Reset count to 0
        end else begin
            if (up_down) begin
                count <= count + 1; // Increment count
            end else begin
                count <= count - 1; // Decrement count
            end
        end
    end
endmodule

up_down_counter/tb_up_down_counter.v
module tb_up_down_counter;
    reg clk;
    reg reset;
    reg up_down;
    wire [3:0] count;

    // Instantiate the up-down counter
    up_down_counter uut (
        .clk(clk),
        .reset(reset),
        .up_down(up_down),
        .count(count)
    );

    // Clock generation
    initial begin
        clk = 0;
        forever #5 clk = ~clk; // 100MHz clock
    end

    initial begin
        // Initialize inputs
        reset = 1; // Assert reset
        up_down = 1; // Count up

        // Monitor outputs
        $monitor("Time: %0dns, Reset: %b, Up/Down: %b, Count: %b", $time, reset, up_down, count);

        // Release reset
        #10 reset = 0;

        // Count up for a few cycles
        #20 up_down = 1; // Count up
        #50 up_down = 0; // Change to count down

        // Count down for a few cycles
        #50 reset = 1; // Assert reset again
        #10 reset = 0; // Release reset

        // Count up again
        #20 up_down = 1; // Count up

        // Finish simulation
        #100;
        $finish;
    end

    initial begin
        $dumpfile("up_down_counter.vcd");
        $dumpvars(0, tb_up_down_counter);
    end
endmodule

up_down_counter/up_down_counter.vcd
$date
	Wed Oct  9 23:18:52 2024
$end
$version
	Icarus Verilog
$end
$timescale
	1ps
$end
$scope module tb_up_down_counter $end
$var wire 4 ! count [3:0] $end
$var reg 1 " clk $end
$var reg 1 # reset $end
$var reg 1 $ up_down $end
$scope module uut $end
$var wire 1 " clk $end
$var wire 1 # reset $end
$var wire 1 $ up_down $end
$var reg 4 % count [3:0] $end
$upscope $end
$upscope $end
$enddefinitions $end
$comment Show the parameter values. $end
$dumpall
$end
#0
$dumpvars
b0 %
1$
1#
0"
b0 !
$end
#5000
1"
#10000
0"
0#
#15000
b1 !
b1 %
1"
#20000
0"
#25000
b10 !
b10 %
1"
#30000
0"
#35000
b11 !
b11 %
1"
#40000
0"
#45000
b100 !
b100 %
1"
#50000
0"
#55000
b101 !
b101 %
1"
#60000
0"
#65000
b110 !
b110 %
1"
#70000
0"
#75000
b111 !
b111 %
1"
#80000
0"
0$
#85000
b110 !
b110 %
1"
#90000
0"
#95000
b101 !
b101 %
1"
#100000
0"
#105000
b100 !
b100 %
1"
#110000
0"
#115000
b11 !
b11 %
1"
#120000
0"
#125000
b10 !
b10 %
1"
#130000
b0 !
b0 %
0"
1#
#135000
1"
#140000
0"
0#
#145000
b1111 !
b1111 %
1"
#150000
0"
#155000
b1110 !
b1110 %
1"
#160000
0"
1$
#165000
b1111 !
b1111 %
1"
#170000
0"
#175000
b0 !
b0 %
1"
#180000
0"
#185000
b1 !
b1 %
1"
#190000
0"
#195000
b10 !
b10 %
1"
#200000
0"
#205000
b11 !
b11 %
1"
#210000
0"
#215000
b100 !
b100 %
1"
#220000
0"
#225000
b101 !
b101 %
1"
#230000
0"
#235000
b110 !
b110 %
1"
#240000
0"
#245000
b111 !
b111 %
1"
#250000
0"
#255000
b1000 !
b1000 %
1"
